{
  "name": "c_M_TD_ZPAY_BANK_DRW_SPC",
  "properties": {
    "description": "/DBMSVC/EMR/TDW/bin/controlm/controlm_month_proc.sh %%PARM1 %%PARM2",
    "folder": {
      "name": "CLOUD_LAKE_DATALAKE_DW_MONTHLY_PROCESSING/DATALAKE_DW_PROCESSING_CL/MONTHLY_JOB_04_CL/0130"
    },
    "annotations": [],
    "activities": [
      {
        "name": "c_M_ZPAY_BANK_DRW_SPC-OUT_DL_CL",
        "type": "ExecutePipeline",
        "typeProperties": {
          "pipeline": {
            "referenceName": "c_M_ZPAY_BANK_DRW_SPC_sh",
            "type": "PipelineReference"
          },
          "waitOnCompletion": true
        }
      },
      {
        "name": "c_M_TD_ZPAY_BANK_DRW_SPC",
        "type": "SetVatiable",
        "typeProperties": {},
        "dependsOn": [
          {
            "activity": "c_M_ZPAY_BANK_DRW_SPC-OUT_DL_CL",
            "dependencyConditions": [
              "Succeeded"
            ]
          }
        ]
      }
    ]
  }
}
